machineLearningModel/__init__.py
machineLearningModel/classifier.py
machineLearningModel/regressor.py
machineLearningModel-1.0.0.dist-info/METADATA
machineLearningModel-1.0.0.dist-info/WHEEL
machineLearningModel-1.0.0.dist-info/top_level.txt
machineLearningModel-1.0.0.dist-info/RECORD
