Metadata-Version: 2.1
Name: machineLearningModel
Version: 1.0.0
Summary: Machine Learning models make simple
Home-page: UNKNOWN
Author: sajo sam
Author-email: <sajosamambalakara@gmail.com>
License: UNKNOWN
Keywords: python,classification,regression,machine learning models,hyper parameter turning
Platform: UNKNOWN
Classifier: Development Status :: 1 - Planning
Classifier: Intended Audience :: Developers
Classifier: Programming Language :: Python :: 3
Classifier: Operating System :: Unix
Classifier: Operating System :: MacOS :: MacOS X
Classifier: Operating System :: Microsoft :: Windows
Requires-Dist: pandas
Requires-Dist: numpy
Requires-Dist: sklearn
Requires-Dist: xgboost
Requires-Dist: scikit-learn
Requires-Dist: matplotlib
Requires-Dist: seaborn
Requires-Dist: scipy
